.gitignore
LICENSE
MANIFEST.in
README.rst
README.txt
setup.py
cs/__init__.py
cs.plonepatches.resourceregistries.egg-info/PKG-INFO
cs.plonepatches.resourceregistries.egg-info/SOURCES.txt
cs.plonepatches.resourceregistries.egg-info/dependency_links.txt
cs.plonepatches.resourceregistries.egg-info/entry_points.txt
cs.plonepatches.resourceregistries.egg-info/namespace_packages.txt
cs.plonepatches.resourceregistries.egg-info/not-zip-safe
cs.plonepatches.resourceregistries.egg-info/requires.txt
cs.plonepatches.resourceregistries.egg-info/top_level.txt
cs/plonepatches/__init__.py
cs/plonepatches/resourceregistries/BaseRegistry.py
cs/plonepatches/resourceregistries/__init__.py
cs/plonepatches/resourceregistries/configure.zcml
cs/plonepatches/resourceregistries/tests.py
cs/plonepatches/resourceregistries/version.txt
docs/HISTORY.txt
docs/INSTALL.txt
docs/LICENSE.GPL
docs/LICENSE.txt