Metadata-Version: 1.1
Name: cs.plonepatches.resourceregistries
Version: 1.0
Summary: A patch for Resource Registries to create a single minified file. Two if the user is logged-in
Home-page: https://github.com/codesyntax/cs.plonepatches.resourceregistries
Author: Mikel Larreategi & Lur Ibargutxi
Author-email: mlarreategi@codesyntax.com
License: GPL
Platform: UNKNOWN
Classifier: Framework :: Plone
Classifier: Programming Language :: Python
